[
    {
        "id": 2,
        "score": 0.17204302549362183
    },
    {
        "id": 4,
        "score": 0.07009345293045044
    },
    {
        "id": 5,
        "score": 0.12087911367416382
    },
    {
        "id": 6,
        "score": 0.053398072719573975
    },
    {
        "id": 7,
        "score": 0.07514452934265137
    },
    {
        "id": 8,
        "score": -0.09890115261077881
    },
    {
        "id": 9,
        "score": 0.03686636686325073
    },
    {
        "id": 12,
        "score": 0.152046799659729
    },
    {
        "id": 13,
        "score": 0.0773809552192688
    },
    {
        "id": 14,
        "score": 0.06951874494552612
    },
    {
        "id": 15,
        "score": 0.16417908668518066
    },
    {
        "id": 17,
        "score": -0.012195110321044922
    },
    {
        "id": 18,
        "score": 0.16243654489517212
    },
    {
        "id": 19,
        "score": -0.020833373069763184
    },
    {
        "id": 20,
        "score": 0.06122446060180664
    },
    {
        "id": 21,
        "score": 0.18285715579986572
    },
    {
        "id": 22,
        "score": 0.09333330392837524
    },
    {
        "id": 23,
        "score": 0.07567566633224487
    },
    {
        "id": 24,
        "score": 0.09090906381607056
    },
    {
        "id": 25,
        "score": 0.07182317972183228
    },
    {
        "id": 26,
        "score": 0.009708762168884277
    },
    {
        "id": 27,
        "score": 0.2596685290336609
    },
    {
        "id": 28,
        "score": 0.21890544891357422
    },
    {
        "id": 29,
        "score": 0.15340906381607056
    },
    {
        "id": 31,
        "score": 0.08499997854232788
    },
    {
        "id": 32,
        "score": -0.05228757858276367
    },
    {
        "id": 36,
        "score": -0.022831082344055176
    },
    {
        "id": 37,
        "score": 0.025641024112701416
    },
    {
        "id": 40,
        "score": -0.10000002384185791
    },
    {
        "id": 41,
        "score": -0.019417524337768555
    },
    {
        "id": 42,
        "score": 0.06111109256744385
    },
    {
        "id": 43,
        "score": 0.08994710445404053
    },
    {
        "id": 44,
        "score": 0.10500001907348633
    },
    {
        "id": 47,
        "score": 0.10507243871688843
    },
    {
        "id": 54,
        "score": -0.005347609519958496
    },
    {
        "id": 56,
        "score": 0.019607841968536377
    },
    {
        "id": 60,
        "score": -0.06306302547454834
    },
    {
        "id": 61,
        "score": 0.3425414562225342
    },
    {
        "id": 62,
        "score": 0.04878050088882446
    },
    {
        "id": 67,
        "score": 0.1860465407371521
    },
    {
        "id": 68,
        "score": -0.045871615409851074
    },
    {
        "id": 69,
        "score": -0.0324324369430542
    },
    {
        "id": 70,
        "score": 0.02489626407623291
    },
    {
        "id": 72,
        "score": 0.0
    },
    {
        "id": 73,
        "score": 0.1111111044883728
    },
    {
        "id": 76,
        "score": -0.004524946212768555
    },
    {
        "id": 77,
        "score": 0.28527605533599854
    },
    {
        "id": 80,
        "score": 0.27319586277008057
    },
    {
        "id": 81,
        "score": 0.0318182110786438
    },
    {
        "id": 84,
        "score": 0.07142859697341919
    },
    {
        "id": 86,
        "score": 0.015625
    },
    {
        "id": 87,
        "score": 0.027932941913604736
    },
    {
        "id": 89,
        "score": 0.057894766330718994
    },
    {
        "id": 97,
        "score": 0.08510637283325195
    },
    {
        "id": 98,
        "score": 0.17511522769927979
    },
    {
        "id": 99,
        "score": 0.03317534923553467
    },
    {
        "id": 100,
        "score": 0.07653063535690308
    },
    {
        "id": 102,
        "score": 0.21835440397262573
    },
    {
        "id": 103,
        "score": 0.10752689838409424
    },
    {
        "id": 104,
        "score": 0.005128204822540283
    },
    {
        "id": 106,
        "score": 0.18888890743255615
    },
    {
        "id": 107,
        "score": 0.12690353393554688
    },
    {
        "id": 109,
        "score": 0.04977375268936157
    },
    {
        "id": 110,
        "score": 0.22360247373580933
    },
    {
        "id": 113,
        "score": 0.10169494152069092
    },
    {
        "id": 114,
        "score": 0.2083333134651184
    },
    {
        "id": 115,
        "score": 0.3359788656234741
    },
    {
        "id": 117,
        "score": 0.22162163257598877
    },
    {
        "id": 118,
        "score": 0.02857142686843872
    },
    {
        "id": 119,
        "score": 0.015706777572631836
    },
    {
        "id": 120,
        "score": 0.07303369045257568
    },
    {
        "id": 121,
        "score": 0.04265403747558594
    },
    {
        "id": 122,
        "score": 0.24193549156188965
    },
    {
        "id": 123,
        "score": 0.09389668703079224
    },
    {
        "id": 124,
        "score": 0.08755761384963989
    },
    {
        "id": 125,
        "score": 0.142011821269989
    },
    {
        "id": 126,
        "score": 0.11282050609588623
    },
    {
        "id": 127,
        "score": 0.23783785104751587
    },
    {
        "id": 130,
        "score": 0.011299431324005127
    },
    {
        "id": 136,
        "score": 0.4119047522544861
    },
    {
        "id": 140,
        "score": 0.09625667333602905
    },
    {
        "id": 141,
        "score": 0.01941746473312378
    },
    {
        "id": 144,
        "score": 0.01554405689239502
    },
    {
        "id": 147,
        "score": 0.14230769872665405
    },
    {
        "id": 148,
        "score": 0.03614455461502075
    },
    {
        "id": 149,
        "score": 0.22834646701812744
    },
    {
        "id": 151,
        "score": 0.3226950168609619
    },
    {
        "id": 153,
        "score": 0.1986755132675171
    },
    {
        "id": 154,
        "score": 0.05056178569793701
    },
    {
        "id": 155,
        "score": 0.058510661125183105
    },
    {
        "id": 156,
        "score": 0.0
    },
    {
        "id": 157,
        "score": -0.05128204822540283
    },
    {
        "id": 158,
        "score": -0.02721083164215088
    },
    {
        "id": 159,
        "score": 0.20858895778656006
    },
    {
        "id": 160,
        "score": 0.02906978130340576
    },
    {
        "id": 161,
        "score": 0.1551724076271057
    },
    {
        "id": 163,
        "score": -0.05925929546356201
    },
    {
        "id": 165,
        "score": 0.07142859697341919
    },
    {
        "id": 168,
        "score": 0.03680980205535889
    },
    {
        "id": 169,
        "score": 0.07567566633224487
    },
    {
        "id": 170,
        "score": 0.35987263917922974
    },
    {
        "id": 171,
        "score": 0.05988025665283203
    },
    {
        "id": 172,
        "score": 0.08823531866073608
    },
    {
        "id": 173,
        "score": 0.0
    },
    {
        "id": 175,
        "score": 0.07185626029968262
    },
    {
        "id": 176,
        "score": 0.18928569555282593
    },
    {
        "id": 177,
        "score": -0.02970302104949951
    },
    {
        "id": 179,
        "score": 0.10162603855133057
    },
    {
        "id": 185,
        "score": 0.16233766078948975
    },
    {
        "id": 186,
        "score": 0.1586207151412964
    },
    {
        "id": 187,
        "score": 0.11643832921981812
    },
    {
        "id": 190,
        "score": 0.20529800653457642
    },
    {
        "id": 193,
        "score": 0.06060606241226196
    },
    {
        "id": 194,
        "score": -0.032258033752441406
    },
    {
        "id": 196,
        "score": 0.08928573131561279
    },
    {
        "id": 197,
        "score": 0.06622517108917236
    },
    {
        "id": 198,
        "score": 0.04878050088882446
    },
    {
        "id": 201,
        "score": 0.1135135293006897
    },
    {
        "id": 202,
        "score": -0.004807710647583008
    },
    {
        "id": 203,
        "score": 0.1803278923034668
    },
    {
        "id": 204,
        "score": 0.05813956260681152
    },
    {
        "id": 205,
        "score": 0.09049773216247559
    },
    {
        "id": 206,
        "score": 0.09852218627929688
    },
    {
        "id": 207,
        "score": 0.1743420958518982
    },
    {
        "id": 208,
        "score": 0.016393423080444336
    },
    {
        "id": 210,
        "score": -0.005181312561035156
    },
    {
        "id": 211,
        "score": 0.31223630905151367
    },
    {
        "id": 213,
        "score": 0.24561405181884766
    },
    {
        "id": 214,
        "score": 0.41463416814804077
    },
    {
        "id": 215,
        "score": -0.10362696647644043
    },
    {
        "id": 218,
        "score": 0.10493826866149902
    },
    {
        "id": 221,
        "score": 0.1785714030265808
    },
    {
        "id": 222,
        "score": 0.05376344919204712
    },
    {
        "id": 225,
        "score": 0.05882352590560913
    },
    {
        "id": 227,
        "score": 0.037634432315826416
    },
    {
        "id": 228,
        "score": 0.06565654277801514
    },
    {
        "id": 230,
        "score": 0.032085537910461426
    },
    {
        "id": 231,
        "score": -0.025125622749328613
    },
    {
        "id": 232,
        "score": -0.04918026924133301
    },
    {
        "id": 233,
        "score": 0.33841460943222046
    },
    {
        "id": 234,
        "score": 0.015789449214935303
    },
    {
        "id": 235,
        "score": 0.09036141633987427
    },
    {
        "id": 236,
        "score": 0.08556151390075684
    },
    {
        "id": 239,
        "score": 0.040816307067871094
    },
    {
        "id": 241,
        "score": 0.12918663024902344
    },
    {
        "id": 242,
        "score": 0.10227274894714355
    },
    {
        "id": 243,
        "score": -0.015075325965881348
    },
    {
        "id": 244,
        "score": 0.010810792446136475
    },
    {
        "id": 245,
        "score": 0.04000002145767212
    },
    {
        "id": 246,
        "score": 0.12365591526031494
    },
    {
        "id": 248,
        "score": 0.18421053886413574
    },
    {
        "id": 249,
        "score": -0.005617976188659668
    },
    {
        "id": 250,
        "score": 0.16564416885375977
    },
    {
        "id": 251,
        "score": 0.0913461446762085
    },
    {
        "id": 255,
        "score": 0.10326087474822998
    },
    {
        "id": 256,
        "score": 0.1045454740524292
    },
    {
        "id": 257,
        "score": 0.022727251052856445
    },
    {
        "id": 261,
        "score": 0.12865495681762695
    },
    {
        "id": 262,
        "score": 0.29629629850387573
    },
    {
        "id": 263,
        "score": 0.14427858591079712
    },
    {
        "id": 264,
        "score": 0.09150326251983643
    },
    {
        "id": 266,
        "score": 0.18579232692718506
    },
    {
        "id": 268,
        "score": -0.07329845428466797
    },
    {
        "id": 269,
        "score": 0.24087589979171753
    },
    {
        "id": 270,
        "score": 0.109375
    },
    {
        "id": 271,
        "score": 0.307692289352417
    },
    {
        "id": 272,
        "score": 0.29230767488479614
    },
    {
        "id": 273,
        "score": 0.059523820877075195
    },
    {
        "id": 280,
        "score": 0.08280253410339355
    },
    {
        "id": 281,
        "score": 0.05228757858276367
    },
    {
        "id": 285,
        "score": 0.3207547068595886
    },
    {
        "id": 286,
        "score": 0.21472394466400146
    },
    {
        "id": 287,
        "score": 0.1666666865348816
    },
    {
        "id": 288,
        "score": 0.02097904682159424
    },
    {
        "id": 289,
        "score": 0.05504584312438965
    },
    {
        "id": 290,
        "score": 0.13450294733047485
    },
    {
        "id": 293,
        "score": -0.06134974956512451
    },
    {
        "id": 295,
        "score": 0.03225809335708618
    },
    {
        "id": 297,
        "score": 0.20430105924606323
    },
    {
        "id": 299,
        "score": 0.19402986764907837
    },
    {
        "id": 300,
        "score": 0.07954543828964233
    }
]