[
    {
        "polish_type": "extreme_minor",
        "file_name": "polished_extreme_minor_llama70b_predictions.json",
        "prediction_labels": {
            "AI": {
                "count": 6,
                "rate": 0.11764705882352941
            },
            "human": {
                "count": 45,
                "rate": 0.8823529411764706
            }
        }
    },
    {
        "polish_type": "minor",
        "file_name": "polished_minor_llama70b_predictions.json",
        "prediction_labels": {
            "AI": {
                "count": 5,
                "rate": 0.09803921568627451
            },
            "human": {
                "count": 46,
                "rate": 0.9019607843137255
            }
        }
    },
    {
        "polish_type": "slight_major",
        "file_name": "polished_slight_major_llama70b_predictions.json",
        "prediction_labels": {
            "AI": {
                "count": 6,
                "rate": 0.12
            },
            "human": {
                "count": 44,
                "rate": 0.88
            }
        }
    },
    {
        "polish_type": "major",
        "file_name": "polished_major_llama70b_predictions.json",
        "prediction_labels": {
            "AI": {
                "count": 11,
                "rate": 0.22
            },
            "human": {
                "count": 39,
                "rate": 0.78
            }
        }
    },
    {
        "polish_type": "average",
        "prediction_labels": {
            "AI": {
                "rate": 0.13892156862745098
            },
            "human": {
                "rate": 0.861078431372549
            }
        }
    }
]